{
  "title": {
    "__TYPE__": "FieldContent",
    "value": "native",
    "type": "Text"
  },
  "description": {
    "__TYPE__": "FieldContent",
    "value": "burn",
    "type": "Text"
  },
  "slices": {
    "__TYPE__": "SliceContentType",
    "value": [
      {
        "key": "selling_points$a9e1c701-7c27-4dcc-92a9-962dcdfeb4f1",
        "name": "selling_points",
        "widget": {
          "__TYPE__": "SharedSliceContent",
          "variation": "default",
          "primary": {},
          "items": [
            {
              "__TYPE__": "GroupItemContent",
              "value": [
                [
                  "selling_points",
                  {
                    "__TYPE__": "LinkContent",
                    "value": {
                      "__TYPE__": "DocumentLink",
                      "id": "mock_document_id"
                    }
                  }
                ]
              ]
            }
          ]
        }
      },
      {
        "key": "tutor_carousel$9810770c-63ee-4440-8f84-d765724745c0",
        "name": "tutor_carousel",
        "widget": {
          "__TYPE__": "SharedSliceContent",
          "variation": "default",
          "primary": {
            "title": {
              "__TYPE__": "FieldContent",
              "value": "toy",
              "type": "Text"
            },
            "tutors_link": {
              "__TYPE__": "LinkContent",
              "value": {
                "__TYPE__": "ExternalLink",
                "url": "http://twitter.com"
              }
            }
          },
          "items": [
            {
              "__TYPE__": "GroupItemContent",
              "value": [
                [
                  "tutor",
                  {
                    "__TYPE__": "LinkContent",
                    "value": {
                      "__TYPE__": "DocumentLink",
                      "id": "mock_document_id"
                    }
                  }
                ]
              ]
            }
          ]
        }
      },
      {
        "key": "hero$3d9adc00-1036-430b-b951-9208680846da",
        "name": "hero",
        "widget": {
          "__TYPE__": "SharedSliceContent",
          "variation": "default",
          "primary": {
            "line_1": {
              "__TYPE__": "StructuredTextContent",
              "value": [
                {
                  "type": "paragraph",
                  "content": {
                    "text": "Lorem aute dolore dolore. Veniam cupidatat mollit ex non."
                  }
                }
              ]
            },
            "line_2": {
              "__TYPE__": "StructuredTextContent",
              "value": [
                {
                  "type": "paragraph",
                  "content": {
                    "text": "Ex aliquip tempor reprehenderit laborum laborum aliqua officia eiusmod exercitation veniam minim laborum aliquip in in."
                  }
                }
              ]
            },
            "line_3": {
              "__TYPE__": "StructuredTextContent",
              "value": [
                {
                  "type": "paragraph",
                  "content": {
                    "text": "Exercitation mollit velit ut ipsum aliqua exercitation dolore cupidatat cupidatat mollit quis dolore voluptate."
                  }
                }
              ]
            },
            "button_1_text": {
              "__TYPE__": "FieldContent",
              "value": "bag",
              "type": "Text"
            },
            "button_1_link": {
              "__TYPE__": "LinkContent",
              "value": {
                "__TYPE__": "ExternalLink",
                "url": "https://slicemachine.dev"
              }
            },
            "button_2_text": {
              "__TYPE__": "FieldContent",
              "value": "visitor",
              "type": "Text"
            },
            "button_2_link": {
              "__TYPE__": "LinkContent",
              "value": {
                "__TYPE__": "ExternalLink",
                "url": "http://twitter.com"
              }
            },
            "background_image": {
              "__TYPE__": "ImageContent",
              "origin": {
                "id": "main",
                "url": "https://images.unsplash.com/photo-1587614295999-6c1c13675117",
                "width": 3810,
                "height": 5715
              },
              "url": "https://images.unsplash.com/photo-1587614295999-6c1c13675117",
              "width": 3810,
              "height": 5715,
              "edit": {
                "zoom": 1,
                "crop": {
                  "x": 0,
                  "y": 0
                },
                "background": "transparent"
              },
              "thumbnails": {}
            }
          },
          "items": [
            {
              "__TYPE__": "GroupItemContent",
              "value": []
            }
          ]
        }
      }
    ]
  }
}